Workbook

Sheet Rebuild Summary
A1: PO Box 13012 Calgary RPO Beltline, AB T2R 1C6 info@luminovas.ca Phone: 587-320-0261
A2: WYNDHAM CROSSING B BUILDING - ABATEMENT | G2: 40762.51
B3: TOTAL
A4: TOTAL - NOT INCLUDING GST | B4: 115250
A6: WYNDHAM CROSSING B BUILDING REBUILD UNITS
B7: TOTAL | C7: UNITS | D7: AVG $/UNIT
A8: BASE SCOPE REBUILD - SEE DETAILED BREAK DOWN | B8: ='Pricing Units Insurance'!E81 -> 0 | C8: 29 | D8: =B8/C8 -> 0
A9: OPTIONAL UPGRADES - SEE DETAILED BREAK DOWN | B9: =#REF! -> #REF! | C9: 29 | D9: =B9/C9 -> #REF!
A10: TOTAL - NOT INCLUDING GST | B10: =SUM(B8:B9) -> #REF! | C10: 29 | D10: =B10/C10 -> #REF! | G10: 692510
G11: 1338420.4
A12: WYNDHAM CROSSING B BUILDING COMMON AREAS | G12: 40762.51
B13: TOTAL
A14: LAUNDRY ROOM - SEE DETAILED BREAK DOWN | B14: =#REF! -> #REF!
A15: STORAGE ROOM - SEE DETAILED BREAK DOWN | B15: =#REF! -> #REF!
A16: HALLWAYS & STAIRWELLS - SEE DETAILED BREAK DOWN | B16: =#REF! -> #REF!
A17: OPTIONAL UPGRADES (REMAINING CEILING TILES) | B17: =ROUNDUP(2889*0.7*40/2/4,2) -> 10111.5 | G17: 115250
A18: TOTAL - NOT INCLUDING GST | B18: =SUM(B14:B16) -> #REF! | G18: =132500/2 -> 66250
G19: 199240.03
A20: TOTAL PROJECT SUMMARY | G20: 35000
B21: CHARGE | C21: COST | D21: PROFIT | G21: 25000
A22: UNITS - BASE SCOPE | B22: =B8 -> 0 | C22: ='Pricing Units Insurance'!#REF! -> #REF! | D22: =B22-C22 -> #REF! | G22: =SUM(G17:G21) -> 440740.03
A23: ABATEMENT | B23: =B4 -> 115250 | C23: 115250 | D23: =B23-C23 -> 0
A24: UNIT UPGRADES | B24: =B9 -> #REF! | C24: =#REF! -> #REF! | D24: =B24-C24 -> #REF!
A25: COMMON AREAS | B25: =B18 -> #REF! | C25: =#REF!+#REF!+#REF! -> #REF! | D25: =B25-C25 -> #REF!
A26: GRAND TOTAL - NOT INCLUDING GST | B26: =SUM(B22:B25) -> #REF! | C26: =SUM(C22:C25) -> #REF! | D26: =SUM(D22:D25) -> #REF!
D27: =D26/B26 -> #REF!
B30: =0.35*B26 -> #REF!
B31: =B30*2 -> #REF!
A35: DESCIPTION | B35: COST
A36: UNIT 1101 | B36: ='Pricing Units Insurance'!D3 -> 63444.02
A37: UNIT 1001 | B37: ='Pricing Units Insurance'!F3 -> 60498.912
A38: UNIT 901 | B38: ='Pricing Units Insurance'!H3 -> 55749.615
A39: UNIT 801 | B39: ='Pricing Units Insurance'!#REF! -> #REF!
A40: UNIT 701 | B40: ='Pricing Units Insurance'!#REF! -> #REF!
A41: EXTERIOR UNIT 1101 AND 1001 | B41: =SUM('Pricing Units Insurance'!#REF!) -> #REF!
A42: HALLWAYS | B42: =SUM('Pricing Units Insurance'!E89:E94) -> 32304
A43: OFFICE | B43: =SUM('Pricing Units Insurance'!E108:E109) -> 11572.5
A44: BOILER ROOM AND ADJACENT HALLWAY | B44: =SUM('Pricing Units Insurance'!#REF!) -> #REF!
A45: Grand Total not including GST | B45: =SUM(B36:B44) -> #REF!

Sheet Pricing Units Insurance
A1: 500 4th Avenue Suite 2500 Calgary , AB T2P 2V6 info@luminovas.ca Phone: 587-320-0261
D2: 3 BED | F2: 2 BED | H2: 1 BED
D3: =SUM(E6:E80) -> 63444.02 | F3: =SUM(G6:G80) -> 60498.912 | H3: =SUM(I6:I80) -> 55749.615
B4: UNIT | C4: RATE | D4: QTY | E4: TOTAL | F4: QTY | G4: TOTAL | H4: QTY | I4: TOTAL | K4: no interior doors
A5: DRYWALL | E5: =TEXT((SUM(E6:E7)),"$0,000.00") -> $14,260.00 | G5: =TEXT((SUM(G6:G7)),"$0,000.00") -> $12,566.70 | I5: =TEXT((SUM(I6:I7)),"$0,000.00") -> $11,022.50
A6: Mud and tape walls | B6: LN FT | C6: 22 | D6: 322 | E6: =$C6*D6 -> 7084 | F6: 288 | G6: =$C6*F6 -> 6336 | H6: 236 | I6: =$C6*H6 -> 5192 | L6: 35401.71 | M6: just insurance
A7: Drywalled Ceiling including Insulation Texture Ceiling | B7: SQFT | C7: 6.9 | D7: 1040 | E7: =$C7*D7 -> 7176 | F7: 903 | G7: =$C7*F7 -> 6230.7 | H7: 845 | I7: =$C7*H7 -> 5830.5 | L7: 40769.71 | M7: new doors, new bathroom (keep bathtub and existing tile)
A8: FINISHING | E8: =TEXT((SUM(E9:E21)),"$0,000.00") -> $9,312.20 | G8: =TEXT((SUM(G9:G21)),"$0,000.00") -> $7,922.50 | I8: =TEXT((SUM(I9:I21)),"$0,000.00") -> $6,237.50
A9: Closet Shelves and Rod (Price per closet/storage room) | B9: EACH | C9: 185 | D9: 6 | E9: =$C9*D9 -> 1110 | F9: 4 | G9: =$C9*F9 -> 740 | H9: 3 | I9: =$C9*H9 -> 555
A10: Doors | B10: EACH | C10: 450 | D10: 5 | E10: =$C10*D10 -> 2250 | F10: 5 | G10: =$C10*F10 -> 2250 | H10: 4 | I10: =$C10*H10 -> 1800
A11: New 20 min fire rated Entry Suite Door | B11: EACH | C11: 1250 | D11: 0 | E11: =$C11*D11 -> 0 | F11: 0 | G11: =$C11*F11 -> 0 | H11: 0 | I11: =$C11*H11 -> 0
A12: Towel bar, toilet paper holder and shower rod | B12: EACH | C12: 190 | D12: 1 | E12: =$C12*D12 -> 190 | F12: 1 | G12: =$C12*F12 -> 190 | H12: 1 | I12: =$C12*H12 -> 190
A13: Door Hardware (handle, hinges, and door stops) | B13: EACH | C13: 95 | D13: 5 | E13: =$C13*D13 -> 475 | F13: 5 | G13: =$C13*F13 -> 475 | H13: 3 | I13: =$C13*H13 -> 285
A14: Mirror | B14: EACH | C14: 200 | D14: 1 | E14: =$C14*D14 -> 200 | F14: 1 | G14: =$C14*F14 -> 200 | H14: 1 | I14: =$C14*H14 -> 200
A15: Closet Doors - Bypass upto 48"W and bifolds upto 36"W | B15: EACH | C15: 350 | D15: 4 | E15: =$C15*D15 -> 1400 | F15: 2 | G15: =$C15*F15 -> 700 | H15: 1 | I15: =$C15*H15 -> 350
A16: Closet Doors - Bypass over 48"W - upto 60"W | B16: EACH | C16: 480 | D16: 0 | E16: =$C16*D16 -> 0 | F16: 0 | G16: =$C16*F16 -> 0 | H16: 0 | I16: =$C16*H16 -> 0
A17: Closet Doors - Bypass over 60"W - upto 72"W | B17: EACH | C17: 490 | D17: 0 | E17: =$C17*D17 -> 0 | F17: 0 | G17: =$C17*F17 -> 0 | H17: 0 | I17: =$C17*H17 -> 0
A18: Closet Doors - Bypass over 72"W - upto 96"W | B18: EACH | C18: 525 | D18: 1 | E18: =$C18*D18 -> 525 | F18: 1 | G18: =$C18*F18 -> 525 | H18: 1 | I18: =$C18*H18 -> 525
A19: Suite Door Closer | B19: EACH | C19: 250 | D19: 1 | E19: =$C19*D19 -> 250 | F19: 1 | G19: =$C19*F19 -> 250 | H19: 1 | I19: =$C19*H19 -> 250
A20: Baseboards MDF as per Spec | B20: LN FT | C20: 4 | D20: =322*1.15 -> 370.3 | E20: =$C20*D20 -> 1481.2 | F20: =ROUNDUP(288*1.15,0) -> 332 | G20: =$C20*F20 -> 1328 | H20: =ROUNDUP(236*1.15,0) -> 272 | I20: =$C20*H20 -> 1088
A21: Window and Door Casing | B21: LN FT | C21: 4.5 | D21: =(54+211)*1.2 -> 318 | E21: =$C21*D21 -> 1431 | F21: =ROUNDUP((210+26+8)*1.15,0) -> 281 | G21: =$C21*F21 -> 1264.5 | H21: =ROUNDUP((175+12+5)*1.15,0) -> 221 | I21: =$C21*H21 -> 994.5
A22: FLOORING | E22: =TEXT((SUM(E23:E25)),"$0,000.00") -> $5,071.32 | G22: =TEXT((SUM(G23:G25)),"$0,000.00") -> $4,235.51 | I22: =TEXT((SUM(I23:I25)),"$0,000.00") -> $3,714.62
A23: Floor Vinyl | B23: SQFT | C23: 4.85 | D23: =40*9*1.15 -> 414 | E23: =$C23*D23 -> 2007.9 | F23: =35*1.15*9 -> 362.25 | G23: =$C23*F23 -> 1756.9125 | H23: =(19+55)*1.15*9 -> 765.9 | I23: =$C23*H23 -> 3714.615
A24: Removal of existing flooring and disposal | B24: SQFT | C24: 0.75 | D24: 0 | E24: =$C24*D24 -> 0 | F24: 0 | G24: =$C24*F24 -> 0 | H24: 0 | I24: =$C24*H24 -> 0
A25: Carpet with underlay | B25: SQFT | C25: 4.5 | D25: =62*9*1.22 -> 680.76 | E25: =$C25*D25 -> 3063.42 | F25: =51*1.2*9 -> 550.8 | G25: =$C25*F25 -> 2478.6 | H25: 0 | I25: =$C25*H25 -> 0
A26: TILING | E26: =TEXT((SUM(E27:E29)),"$0,000.00") -> $0,350.00 | G26: =TEXT((SUM(G27:G29)),"$0,000.00") -> $0,350.00 | I26: =TEXT((SUM(I27:I29)),"$0,000.00") -> $0,350.00
A27: Tile Tub Surround (sq ft) | B27: SQFT | C27: 18 | D27: 0 | E27: =$C27*D27 -> 0 | F27: 0 | G27: =$C27*F27 -> 0 | H27: 0 | I27: =$C27*H27 -> 0
A28: 5-Piece Alcove Polystyrene Tub Surround | B28: LOT | C28: 350 | D28: 1 | E28: =$C28*D28 -> 350 | F28: 1 | G28: =$C28*F28 -> 350 | H28: 1 | I28: =$C28*H28 -> 350
A29: Back Splash (sq ft) - Kitchen and Vanity | B29: SQFT | C29: 18 | D29: 0 | E29: =$C29*D29 -> 0 | F29: 0 | G29: =$C29*F29 -> 0 | H29: 0 | I29: =$C29*H29 -> 0
A30: CABINETS | E30: =TEXT((SUM(E31:E35)),"$0,000.00") -> $5,415.00 | G30: =TEXT((SUM(G31:G35)),"$0,000.00") -> $7,335.00 | I30: =TEXT((SUM(I31:I35)),"$0,000.00") -> $6,935.00
A31: Kitchen Cabinets upper and lower (linear ft) | B31: LN FT | C31: 295 | D31: 12 | E31: =$C31*D31 -> 3540 | F31: 16 | G31: =$C31*F31 -> 4720 | H31: 16 | I31: =$C31*H31 -> 4720
A32: Kitchen Island | B32: Lot | C32: 1200 | D32: 0 | E32: =$C32*D32 -> 0 | F32: 0 | G32: =$C32*F32 -> 0 | H32: 0 | I32: =$C32*H32 -> 0
A33: Kitchen Counters (linear ft) | B33: LN FT | C33: 85 | D33: 12 | E33: =$C33*D33 -> 1020 | F33: 16 | G33: =$C33*F33 -> 1360 | H33: 16 | I33: =$C33*H33 -> 1360
A34: Bathroom Vanity (3 ft) | B34: EACH | C34: =855 -> 855 | D34: 1 | E34: =$C34*D34 -> 855 | F34: 0 | G34: =$C34*F34 -> 0 | H34: 1 | I34: =$C34*H34 -> 855
A35: Bathroom Vanity (>3 ft) | B35: EACH | C35: =1255 -> 1255 | D35: 0 | E35: =$C35*D35 -> 0 | F35: 1 | G35: =$C35*F35 -> 1255 | H35: 0 | I35: =$C35*H35 -> 0
A36: PLUMBING | E36: =TEXT((SUM(E37:E44)),"$0,000.00") -> $4,350.00 | G36: =TEXT((SUM(G37:G44)),"$0,000.00") -> $4,350.00 | I36: =TEXT((SUM(I37:I44)),"$0,000.00") -> $4,350.00
A37: Kitchen Sink - w/ p trap | B37: EACH | C37: 590 | D37: 1 | E37: =$C37*D37 -> 590 | F37: 1 | G37: =$C37*F37 -> 590 | H37: 1 | I37: =$C37*H37 -> 590
A38: Kitchen Faucet | B38: EACH | C38: 375 | D38: 1 | E38: =$C38*D38 -> 375 | F38: 1 | G38: =$C38*F38 -> 375 | H38: 1 | I38: =$C38*H38 -> 375
A39: New Tub | B39: EACH | C39: 1050 | D39: 1 | E39: =$C39*D39 -> 1050 | F39: 1 | G39: =$C39*F39 -> 1050 | H39: 1 | I39: =$C39*H39 -> 1050
A40: New Shower Valve and Trim Kit; includes Rough-in | B40: EACH | C40: 655 | D40: 1 | E40: =$C40*D40 -> 655 | F40: 1 | G40: =$C40*F40 -> 655 | H40: 1 | I40: =$C40*H40 -> 655
A41: Shut off valves | B41: EACH | C41: 95 | D41: 5 | E41: =$C41*D41 -> 475 | F41: 5 | G41: =$C41*F41 -> 475 | H41: 5 | I41: =$C41*H41 -> 475
A42: Bathroom Sink - w/ p trap | B42: EACH | C42: 325 | D42: 1 | E42: =$C42*D42 -> 325 | F42: 1 | G42: =$C42*F42 -> 325 | H42: 1 | I42: =$C42*H42 -> 325
A43: Bathroom Faucet | B43: EACH | C43: 290 | D43: 1 | E43: =$C43*D43 -> 290 | F43: 1 | G43: =$C43*F43 -> 290 | H43: 1 | I43: =$C43*H43 -> 290
A44: Toilet New - Standard | B44: EACH | C44: 590 | D44: 1 | E44: =$C44*D44 -> 590 | F44: 1 | G44: =$C44*F44 -> 590 | H44: 1 | I44: =$C44*H44 -> 590
A45: ELECTRICAL | E45: =TEXT((SUM(E46:E59)),"$0,000.00") -> $6,219.00 | G45: =TEXT((SUM(G46:G59)),"$0,000.00") -> $5,944.00 | I45: =TEXT((SUM(I46:I59)),"$0,000.00") -> $5,629.00 | N45: =E45*6+G45*5+I45 -> 72663
A46: 120v Receptacles | B46: EACH | C46: 40 | D46: 23 | E46: =$C46*D46 -> 920 | F46: 17 | G46: =$C46*F46 -> 680 | H46: 13 | I46: =$C46*H46 -> 520
A47: 240v Receptacles | B47: EACH | C47: 120 | D47: 1 | E47: =$C47*D47 -> 120 | F47: 1 | G47: =$C47*F47 -> 120 | H47: 1 | I47: =$C47*H47 -> 120
A48: 120v GFCI Receptacles | B48: EACH | C48: 80 | D48: 2 | E48: =$C48*D48 -> 160 | F48: 3 | G48: =$C48*F48 -> 240 | H48: 3 | I48: =$C48*H48 -> 240
A49: Light Switches | B49: EACH | C49: 40 | D49: 12 | E49: =$C49*D49 -> 480 | F49: 11 | G49: =$C49*F49 -> 440 | H49: 9 | I49: =$C49*H49 -> 360
A50: Cable & Phone Jack Covers | B50: EACH | C50: 15 | D50: 2 | E50: =$C50*D50 -> 30 | F50: 2 | G50: =$C50*F50 -> 30 | H50: 2 | I50: =$C50*H50 -> 30
A51: Replace KITCHEN wire only. Upgrade to current code | B51: EACH | C51: 1100 | D51: 1 | E51: =$C51*D51 -> 1100 | F51: 1 | G51: =$C51*F51 -> 1100 | H51: 1 | I51: =$C51*H51 -> 1100
A52: Replace electrical Panel | B52: EACH | C52: 1500 | D52: 1 | E52: =$C52*D52 -> 1500 | F52: 1 | G52: =$C52*F52 -> 1500 | H52: 1 | I52: =$C52*H52 -> 1500
A53: Replace Thermostat | B53: EACH | C53: 110 | D53: 1 | E53: =$C53*D53 -> 110 | F53: 1 | G53: =$C53*F53 -> 110 | H53: 1 | I53: =$C53*H53 -> 110
A54: Light Fixture - Vanity Light | B54: EACH | C54: 289 | D54: 1 | E54: =$C54*D54 -> 289 | F54: 1 | G54: =$C54*F54 -> 289 | H54: 1 | I54: =$C54*H54 -> 289
A55: Light Fixture - Surface Mount Globe or wall mount light | B55: EACH | C55: 75 | D55: 7 | E55: =$C55*D55 -> 525 | F55: 6 | G55: =$C55*F55 -> 450 | H55: 5 | I55: =$C55*H55 -> 375
A56: Light Fixture - Kitchen | B56: EACH | C56: 250 | D56: 2 | E56: =$C56*D56 -> 500 | F56: 2 | G56: =$C56*F56 -> 500 | H56: 2 | I56: =$C56*H56 -> 500
A57: Replace Smoke/CO Detector | B57: EACH | C57: 110 | D57: 1 | E57: =$C57*D57 -> 110 | F57: 1 | G57: =$C57*F57 -> 110 | H57: 1 | I57: =$C57*H57 -> 110
... A59: USB Receptacle | B59: EACH | C59: 80 | D59: 1 | E59: =$C59*D59 -> 80 | F59: 1 | G59: =$C59*F59 -> 80 | H59: 1 | I59: =$C59*H59 -> 80
A60: PAINTING | E60: =TEXT((SUM(E61:E63)),"$0,000.00") -> $4,680.00 | G60: =TEXT((SUM(G61:G63)),"$0,000.00") -> $4,063.50 | I60: =TEXT((SUM(I61:I63)),"$0,000.00") -> $3,802.50
A61: Paint Walls, Doors, Trim | B61: SQFT | C61: 2.5 | D61: 1040 | E61: =$C61*D61 -> 2600 | F61: 903 | G61: =$C61*F61 -> 2257.5 | H61: 845 | I61: =$C61*H61 -> 2112.5
A62: Primer | B62: SQFT | C62: 1 | D62: 1040 | E62: =$C62*D62 -> 1040 | F62: 903 | G62: =$C62*F62 -> 903 | H62: 845 | I62: =$C62*H62 -> 845
A63: Paint Ceiling | B63: SQFT | C63: 1 | D63: 1040 | E63: =$C63*D63 -> 1040 | F63: 903 | G63: =$C63*F63 -> 903 | H63: 845 | I63: =$C63*H63 -> 845
A64: CLEANING | E64: =TEXT((SUM(E65)),"$0,000.00") -> $0,416.00 | G64: =TEXT((SUM(G65)),"$0,000.00") -> $0,361.20 | I64: =TEXT((SUM(I65)),"$0,000.00") -> $0,338.00
A65: Move-in Ready | B65: SQFT | C65: 0.4 | D65: 1040 | E65: =$C65*D65 -> 416 | F65: 903 | G65: =$C65*F65 -> 361.2 | H65: 845 | I65: =$C65*H65 -> 338
A66: APPLIANCES | E66: =TEXT((SUM(E67:E70)),"$0,000.00") -> $2,470.50 | G66: =TEXT((SUM(G67:G70)),"$0,000.00") -> $2,470.50 | I66: =TEXT((SUM(I67:I70)),"$0,000.00") -> $2,470.50
A67: Range, Fridge, and Hood fan - Stainless Steel | B67: SET | C67: =1002.75+897.75+220+250-100 -> 2270.5 | D67: 1 | E67: =$C67*D67 -> 2270.5 | F67: 1 | G67: =$C67*F67 -> 2270.5 | H67: 1 | I67: =$C67*H67 -> 2270.5
A68: Dishwasher - Supply and Install - Stainless Steel | B68: EACH | C68: =719.25+100 -> 819.25 | D68: 0 | E68: =$C68*D68 -> 0 | F68: 0 | G68: =$C68*F68 -> 0 | H68: 0 | I68: =$C68*H68 -> 0
A69: Appliance Install | B69: EACH | C69: 100 | D69: 1 | E69: =$C69*D69 -> 100 | F69: 1 | G69: =$C69*F69 -> 100 | H69: 1 | I69: =$C69*H69 -> 100
A70: Hood Fan Installation | B70: EACH | C70: 100 | D70: 1 | E70: =$C70*D70 -> 100 | F70: 1 | G70: =$C70*F70 -> 100 | H70: 1 | I70: =$C70*H70 -> 100
A71: BLINDS | E71: =TEXT((SUM(E72:E73)),"$0,000.00") -> $0,000.00 | G71: =TEXT((SUM(G72:G73)),"$0,000.00") -> $0,000.00 | I71: =TEXT((SUM(I72:I73)),"$0,000.00") -> $0,000.00
A72: Horizontal | B72: EACH | C72: 350 | D72: 0 | E72: =$C72*D72 -> 0 | F72: 0 | G72: =$C72*F72 -> 0 | H72: 0 | I72: =$C72*H72 -> 0
A73: Vertical | B73: EACH | C73: 425 | D73: 0 | E73: =$C73*D73 -> 0 | F73: 0 | G73: =$C73*F73 -> 0 | H73: 0 | I73: =$C73*H73 -> 0
A74: MISCELLANEOUS | E74: =TEXT((SUM(E75:E80)),"$0,000.00") -> $10,900.00 | G74: =TEXT((SUM(G75:G80)),"$0,000.00") -> $10,900.00 | I74: =TEXT((SUM(I75:I80)),"$0,000.00") -> $10,900.00
A75: Demo and Disposal | B75: PER UNIT | C75: 2500 | D75: 0 | E75: =$C75*D75 -> 0 | F75: 0 | G75: =$C75*F75 -> 0 | H75: 0 | I75: =$C75*H75 -> 0
A76: New Window AC units | B76: PER UNIT | C76: 750 | D76: 1 | E76: =$C76*D76 -> 750 | F76: 1 | G76: =$C76*F76 -> 750 | H76: 1 | I76: =$C76*H76 -> 750
A77: Contingency | B77: PER UNIT | C77: 1500 | D77: 1 | E77: =$C77*D77 -> 1500 | F77: 1 | G77: =$C77*F77 -> 1500 | H77: 1 | I77: =$C77*H77 -> 1500
A78: General Conditions - Site Security, Delivery, and Storage | B78: PER UNIT | C78: 2650 | D78: 1 | E78: =$C78*D78 -> 2650 | F78: 1 | G78: =$C78*F78 -> 2650 | H78: 1 | I78: =$C78*H78 -> 2650
A79: Long distance surcharge (greater than 3hrs from Calgary) | B79: PER UNIT | C79: 3000 | D79: 1 | E79: =$C79*D79 -> 3000 | F79: 1 | G79: =$C79*F79 -> 3000 | H79: 1 | I79: =$C79*H79 -> 3000
A80: Supervision | B80: PER UNIT | C80: 3000 | D80: 1 | E80: =$C80*D80 -> 3000 | F80: 1 | G80: =$C80*F80 -> 3000 | H80: 1 | I80: =$C80*H80 -> 3000
E81: =$C81*D81 -> 0 | G81: =$C81*F81 -> 0 | I81: =$C81*H81 -> 0
A83: UNIT SUMMARY | E83: =TEXT((SUM(E84:E86)),"$0,000.00") -> $738,908.30
A84: 3 BEDROOM | B84: EACH | C84: =D3 -> 63444.02 | D84: 6 | E84: =$C84*D84 -> 380664.12
A85: 2 BEDROOM | B85: EACH | C85: =F3 -> 60498.912 | D85: 5 | E85: =$C85*D85 -> 302494.56 | I85: =6*SUM(E6:E7) -> 85560
A86: 1 BEDROOM | B86: EACH | C86: =H3 -> 55749.615 | D86: 1 | E86: =$C86*D86 -> 55749.615 | I86: =5*SUM(G6:G7) -> 62833.5
I87: =SUM(I6:I7) -> 11022.5
A88: COMMON AREA | E88: =TEXT((SUM(E89:E105)),"$0,000.00") -> $65,494.77 | I88: =E89+E90 -> 22228
A89: Drywall in hallways and landings - Walls | B89: LN FT | C89: 32 | D89: 410 | E89: =$C89*D89 -> 13120 | I89: =SUM(I85:I88) -> 181644
A90: Drywall in hallways and landings - Ceilings | B90: SQFT | C90: 6.9 | D90: =390*3+150 -> 1320 | E90: =$C90*D90 -> 9108 | I90: =I89+E110+E93+E63*6+G63*5+I63 -> 209249 | N90: =I90-176273.47 -> 32975.53
A91: Paint Walls, Doors, Trim | B91: HALL | C91: 1850 | D91: 3 | E91: =$C91*D91 -> 5550
A92: Primer | B92: SQFT | C92: 1 | D92: =390*3+150 -> 1320 | E92: =$C92*D92 -> 1320
A93: Paint Ceiling | B93: SQFT | C93: 1 | D93: =390*3+150 -> 1320 | E93: =$C93*D93 -> 1320
A94: Baseboards | B94: per lnft | C94: 4 | D94: =410*1.15 -> 471.5 | E94: =$C94*D94 -> 1886
A95: 120v Receptacles | B95: EACH | C95: 40 | D95: 6 | E95: =$C95*D95 -> 240 | I95: =E45*6+G45*5+I45+E95+E96+E97+E98+E99+E100 -> 84283
A96: 240v Receptacles | B96: EACH | C96: 120 | D96: 1 | E96: =$C96*D96 -> 120
A97: Light Switches | B97: EACH | C97: 40 | D97: 4 | E97: =$C97*D97 -> 160 | I97: =I95/12 -> 7023.5833
A98: Light Fixture - Surface Mount Globe or wall mount light | B98: EACH | C98: 75 | D98: 12 | E98: =$C98*D98 -> 900 | I98: =I95/1.3 -> 64833.077
A99: Electrical commisioning and life safety | B99: LOT | C99: 6400 | D99: 1 | E99: =$C99*D99 -> 6400 | I99: =38824.88/12 -> 3235.4067
A100: Replace all burned or damage electrical wiring | B100: LOT | C100: 3800 | D100: 1 | E100: =$C100*D100 -> 3800 | I100: =4500*12 -> 54000
A101: Carpet Tile | B101: per sqft | C101: 4.85 | D101: 472 | E101: =$C101*D101 -> 2289.2
A102: VCT Tile | B102: per sqft | C102: 4.85 | D102: 150 | E102: =$C102*D102 -> 727.5
...

Sheet Pricing UNITS Combined
A1: PO Box 13012 Calgary RPO Beltline, AB T2R 1C6 info@luminovas.ca Phone: 587-320-0261
B2: UNITS | C2: QTY | D2: RATE | E2: TOTAL | F2: OUR COST | G2: PROFIT
A3: DRYWALL | E3: =TEXT((SUM(E4:E7)),"$0,000.00") -> $205,115.50 | F3: =TEXT((SUM(F4:F7)),"$0,000.00") -> $199,240.03 | G3: =TEXT((SUM(G4:G7)),"$0,000.00") -> $5,875.47
A4: up to 2 ft | B4: LN FT | C4: 5250 | D4: 18 | E4: =D4*C4 -> 94500 | F4: 92157 | G4: =E4-F4 -> 2343
A5: Float Wall to Flat Texture | B5: SQFT | C5: 59937 | D5: 1.5 | E5: =D5*C5 -> 89905.5 | F5: 87676.41 | G5: =E5-F5 -> 2229.09
A6: Drywalled Ceiling including Insulation Texture Ceiling | B6: SQFT | C6: 900 | D6: 6.9 | E6: =D6*C6 -> 6210 | F6: 5266.12 | G6: =E6-F6 -> 943.88
A7: Tub Surround Boarding | B7: EACH | C7: 29 | D7: 500 | E7: =D7*C7 -> 14500 | F7: 14140.5 | G7: =E7-F7 -> 359.5
A8: FINISHING | E8: =TEXT((SUM(E9:E21)),"$0,000.00") -> $145,977.00 | F8: =TEXT((SUM(F9:F21)),"$0,000.00") -> $97,628.52 | G8: =TEXT((SUM(G9:G12)),"$0,000.00") -> $4,350.00
A9: Doors | B9: EACH | C9: 0 | D9: 290 | E9: =D9*C9 -> 0 | G9: =E9-F9 -> 0
A10: New fire rated Entry Suite Door | B10: EACH | C10: 0 | D10: 1800 | E10: =D10*C10 -> 0 | G10: =E10-F10 -> 0
A11: Closet Shelves and Rod (Price per closet/storage room) | B11: EACH | C11: =84+29 -> 113 | D11: 180 | E11: =D11*C11 -> 20340 | F11: =3480+13380 -> 16860 | G11: =E11-F11 -> 3480
A12: Towel bar, toilet paper holder and shower rod | B12: EACH | C12: =29 -> 29 | D12: 190 | E12: =D12*C12 -> 5510 | F12: =(85+75)*29 -> 4640 | G12: =E12-F12 -> 870
A13: Closet Doors - Bypass upto 48"W and bifolds upto 36"W | B13: EACH | C13: 7 | D13: 350 | E13: =D13*C13 -> 2450 | F13: 1992.66 | G13: =E13-F13 -> 457.34
A14: Closet Doors - Bypass over 48"W - upto 60"W | B14: EACH | C14: 22 | D14: 480 | E14: =D14*C14 -> 10560 | F14: 8588.75 | G14: =E14-F14 -> 1971.25
A15: Closet Doors - Bypass over 60"W - upto 72"W | B15: EACH | C15: 22 | D15: 490 | E15: =D15*C15 -> 10780 | F15: 8767.69 | G15: =E15-F15 -> 2012.31
A16: Closet Doors - Bypass over 72"W - upto 96"W | B16: EACH | C16: 33 | D16: 525 | E16: =D16*C16 -> 17325 | F16: 14090.92 | G16: =E16-F16 -> 3234.08
A17: Suite Door Closer | B17: EACH | C17: 29 | D17: 110 | E17: =D17*C17 -> 3190 | F17: =50*29 -> 1450 | G17: =E17-F17 -> 1740
A18: Door Hardware (handle, hinges, and door stops) | B18: EACH | C18: =4*29 -> 116 | D18: 56 | E18: =D18*C18 -> 6496 | F18: =27*C18 -> 3132 | G18: =E18-F18 -> 3364
A19: Baseboards | B19: LN FT | C19: 7250 | D19: 4 | E19: =D19*C19 -> 29000 | F19: =1.1*C19+700*29/2 -> 18125 | G19: =E19-F19 -> 10875
A20: Window and Door Casing | B20: LN FT | C20: 9284 | D20: 4 | E20: =D20*C20 -> 37136 | F20: =0.85*C20+700*29/2 -> 18041.4 | G20: =E20-F20 -> 19094.6
A21: Mirror | B21: EACH | C21: 29 | D21: 110 | E21: =D21*C21 -> 3190 | F21: =66.9*C21 -> 1940.1 | G21: =E21-F21 -> 1249.9
A22: FLOORING | E22: =TEXT((SUM(E23:E25)),"$0,000.00") -> $112,569.60 | F22: =TEXT((SUM(F23:F25)),"$0,000.00") -> $85,001.26 | G22: =TEXT((SUM(G23:G25)),"$0,000.00") -> $27,568.34
A23: Floor Vinyl | B23: SQFT | C23: 12516 | D23: 4.85 | E23: =D23*C23 -> 60702.6 | F23: 45043.5 | G23: =E23-F23 -> 15659.1
A24: Removal of existing flooring and disposal | B24: SQFT | C24: 0 | D24: 0.75 | E24: =D24*C24 -> 0 | F24: =2850/2 -> 1425 | G24: =E24-F24 -> -1425
A25: Carpet with underlay | B25: SQFT | C25: 11526 | D25: 4.5 | E25: =D25*C25 -> 51867 | F25: 38532.76 | G25: =E25-F25 -> 13334.24
A26: TILING | E26: =TEXT((SUM(E27:E28)),"$0,000.00") -> $23,345.00 | F26: =TEXT((SUM(F27:F28)),"$0,000.00") -> $23,200.00 | G26: =TEXT((SUM(G27:G28)),"$0,000.00") -> $0,145.00
A27: Tile Tub Surround (sq ft) | B27: SQFT | C27: =70*29 -> 2030 | D27: 11.5 | E27: =D27*C27 -> 23345 | F27: =800*29 -> 23200 | G27: =E27-F27 -> 145
A28: Back Splash (sq ft) - Kitchen and Vanity | B28: SQFT | C28: 0 | D28: 11.5 | E28: =D28*C28 -> 0 | G28: =E28-F28 -> 0
A29: CABINETS | E29: =TEXT((SUM(E30:E32)),"$0,000.00") -> $189,515.00 | F29: =TEXT((SUM(F30:F32)),"$0,000.00") -> $132,500.00 | G29: =TEXT((SUM(G30:G32)),"$0,000.00") -> $57,015.00
A30: Kitchen Cabinets (upper & lower) (linear ft) | B30: LN FT | C30: =29*16 -> 464 | D30: 295 | E30: =D30*C30 -> 136880 | F30: 132500 | G30: =E30-F30 -> 4380
A31: Kitchen Counters (linear ft) | B31: LN FT | C31: =C30 -> 464 | D31: 60 | E31: =D31*C31 -> 27840 | G31: =E31-F31 -> 27840
A32: Bathroom Vanity (3 ft) | B32: EACH | C32: 29 | D32: 855 | E32: =D32*C32 -> 24795 | G32: =E32-F32 -> 24795
A33: PLUMBING | E33: =TEXT((SUM(E34:E42)),"$0,000.00") -> $92,930.00 | F33: =TEXT((SUM(F34:F42)),"$0,000.00") -> $68,975.95 | G33: =TEXT((SUM(G34:G42)),"$0,000.00") -> $23,954.05
A34: Kitchen Sink - w/ p trap | B34: EACH | C34: 29 | D34: 590 | E34: =D34*C34 -> 17110 | F34: 12670.287 | G34: =E34-F34 -> 4439.7131
A35: Shut off valves | B35: EACH | C35: =29*7 -> 203 | D35: 70 | E35: =D35*C35 -> 14210 | F35: 10522.781 | G35: =E35-F35 -> 3687.2194
A36: Kitchen Faucet | B36: EACH | C36: 29 | D36: 300 | E36: =D36*C36 -> 8700 | F36: 6442.5187 | G36: =E36-F36 -> 2257.4813
A37: Bathroom Sink - w/ p trap | B37: EACH | C37: 29 | D37: 325 | E37: =D37*C37 -> 9425 | F37: 6979.3953 | G37: =E37-F37 -> 2445.6047
A38: Bathroom Faucet | B38: EACH | C38: 29 | D38: 290 | E38: =D38*C38 -> 8410 | F38: 6227.7681 | G38: =E38-F38 -> 2182.2319
A39: New Tub | B39: EACH | C39: 0 | D39: 900 | E39: =D39*C39 -> 0 | F39: 0 | G39: =E39-F39 -> 0
A40: New Shower Valve and Trim Kit; includes Rough-in | B40: EACH | C40: 29 | D40: 585 | E40: =D40*C40 -> 16965 | F40: 12562.912 | G40: =E40-F40 -> 4402.0884
A41: 24" x 24" Janitor Sink | B41: EACH | C41: 1 | D41: 1000 | E41: =D41*C41 -> 1000 | F41: 900 | G41: =E41-F41 -> 100
A42: Toilet New - Standard | B42: EACH | C42: 29 | D42: 590 | E42: =D42*C42 -> 17110 | F42: 12670.287 | G42: =E42-F42 -> 4439.7131
A43: ELECTRICAL | E43: =TEXT((SUM(E44:E56)),"$0,000.00") -> $79,567.00 | F43: =TEXT((SUM(F44:F56)),"$0,000.00") -> $74,820.01 | G43: =TEXT((SUM(G44:G56)),"$0,000.00") -> $4,746.99
A44: 120v Receptacles | B44: EACH | C44: 408 | D44: 20 | E44: =D44*C44 -> 8160 | F44: 43065 | G44: =E44-F44 -> -34905
A45: 120v GFCI Receptacles | B45: EACH | C45: 116 | D45: 95 | E45: =D45*C45 -> 11020 | G45: =E45-F45 -> 11020
A46: Light Switches | B46: EACH | C46: 226 | D46: 20 | E46: =D46*C46 -> 4520 | G46: =E46-F46 -> 4520
A47: Cable & Phone Jack Covers | B47: EACH | C47: =29*3 -> 87 | D47: 20 | E47: =D47*C47 -> 1740 | G47: =E47-F47 -> 1740
A48: Light Fixture - Vanity Light | B48: EACH | C48: 29 | D48: 289 | E48: =D48*C48 -> 8381 | F48: 8309.04 | G48: =E48-F48 -> 71.96
A49: Replace Thermostat | B49: EACH | C49: 29 | D49: 65 | E49: =D49*C49 -> 1885 | G49: =E49-F49 -> 1885
A50: Light Fixture - Surface Mount Globe | B50: EACH | C50: 127 | D50: 75 | E50: =D50*C50 -> 9525 | F50: 9443.22 | G50: =E50-F50 -> 81.78
A51: Light Fixture - Kitchen | B51: EACH | C51: 29 | D51: 250 | E51: =D51*C51 -> 7250 | F51: 7187.75 | G51: =E51-F51 -> 62.25
A52: Replace Smoke/CO Detector | B52: EACH | C52: 29 | D52: 95 | E52: =D52*C52 -> 2755 | G52: =E52-F52 -> 2755
A53: Supply and install Bathroom Fan | B53: EACH | C53: 29 | D53: 175 | E53: =D53*C53 -> 5075 | F53: 4060 | G53: =E53-F53 -> 1015
A54: Relocate Range Outlet | B54: EACH | C54: 29 | D54: 300 | E54: =D54*C54 -> 8700 | G54: =E54-F54 -> 8700
A55: Run Power for Dishwasher | B55: EACH | C55: 29 | D55: 250 | E55: =D55*C55 -> 7250 | F55: 2755 | G55: =E55-F55 -> 4495
A56: USB Receptacle | B56: EACH | C56: =29*2 -> 58 | D56: 57 | E56: =D56*C56 -> 3306 | G56: =E56-F56 -> 3306
A57: PAINTING | E57: =TEXT((SUM(E58:E60)),"$0,000.00") -> $83,164.00 | F57: =TEXT((SUM(F58:F60)),"$0,000.00") -> $67,903.41 | G57: =TEXT((SUM(G58:G60)),"$0,000.00") -> $15,260.59
A58: Paint Walls, Doors, Trim | B58: SQFT | C58: 20791 | D58: 2.5 | E58: =D58*C58 -> 51977.5 | F58: =2.3*C58*0.92 -> 43993.756 | G58: =E58-F58 -> 7983.744
A59: Kilz Primer | B59: SQFT | C59: 20791 | D59: 0.5 | E59: =D59*C59 -> 10395.5 | F59: =C59*0.92*0.25 -> 4781.93 | G59: =E59-F59 -> 5613.57
A60: Paint Ceiling | B60: SQFT | C60: 20791 | D60: 1 | E60: =D60*C60 -> 20791 | F60: =1*0.92*C60 -> 19127.72 | G60: =E60-F60 -> 1663.28
A61: BLINDS | E61: =TEXT((SUM(E62:E63)),"$0,000.00") -> $32,275.00 | F61: =TEXT((SUM(F62:F63)),"$0,000.00") -> $22,496.00 | G61: =TEXT((SUM(G62:G63)),"$0,000.00") -> $9,779.00
A62: Horizontal | B62: EACH | C62: 57 | D62: 350 | E62: =D62*C62 -> 19950 | F62: =240*C62 -> 13680 | G62: =E62-F62 -> 6270
A63: Vertical | B63: EACH | C63: =29 -> 29 | D63: 425 | E63: =D63*C63 -> 12325 | F63: =304*C63 -> 8816 | G63: =E63-F63 -> 3509
A64: CLEANING | E64: =TEXT((SUM(E65)),"$0,000.00") -> $8,316.40 | F64: =TEXT((SUM(F65)),"$0,000.00") -> $8,316.40 | G64: =TEXT((SUM(G65)),"$0,000.00") -> $0,000.00
A65: Move-in Ready | B65: SQFT | C65: 20791 | D65: 0.4 | E65: =D65*C65 -> 8316.4 | F65: =E65 -> 8316.4 | G65: =E65-F65 -> 0
A66: APPLIANCES | E66: =TEXT((SUM(E67:E70)),"$0,000.00") -> $95,402.75 | F66: =TEXT((SUM(F67:F70)),"$0,000.00") -> $67,135.00 | G66: =TEXT((SUM(G67:G70)),"$0,000.00") -> $28,267.75
A67: Range, Fridge, and Hood fan - Stainless Steel | B67: SET | C67: 29 | D67: =1002.75+897.75+220+250-100 -> 2270.5 | E67: =D67*C67 -> 65844.5 | F67: =1780*29 -> 51620 | G67: =E67-F67 -> 14224.5
A68: Dishwasher - Supply and Install - Stainless Steel | B68: EACH | C68: 29 | D68: =719.25+100 -> 819.25 | E68: =D68*C68 -> 23758.25 | F68: =435*29 -> 12615 | G68: =E68-F68 -> 11143.25
A69: Appliance Install | B69: EACH | C69: 29 | D69: 100 | E69: =D69*C69 -> 2900 | F69: 2900 | G69: =E69-F69 -> 0
A70: Hood Fan Installation | B70: EACH | C70: 29 | D70: 100 | E70: =D70*C70 -> 2900 | G70: =E70-F70 -> 2900
A71: MISCELLANEOUS | E71: =TEXT((SUM(E72:E74)),"$0,000.00") -> $207,350.00 | F71: =TEXT((SUM(F72:F74)),"$0,000.00") -> $32,500.00 | G71: =TEXT((SUM(G72:G74)),"$0,000.00") -> $174,850.00
A72: Contingency | B72: PER UNIT | C72: 29 | D72: 1500 | E72: =D72*C72 -> 43500 | G72: =E72-F72 -> 43500
A73: General on site labour | B73: PER UNIT | C73: 29 | D73: 2650 | E73: =D73*C73 -> 76850 | G73: =E73-F73 -> 76850
A74: Supervision | B74: PER UNIT | C74: 29 | D74: 3000 | E74: =D74*C74 -> 87000 | F74: 32500 | G74: =E74-F74 -> 54500
E75: =SUM(E3:E74) -> 1275527.2 | F75: =SUM(F3:F74) -> 879716.57 | G75: =SUM(G3:G74) -> 395810.68
E82: =SUM(#REF!+'Rebuild Summary'!#REF!) -> #REF! | F82: =SUM(#REF!+'Rebuild Summary'!#REF!) -> #REF! | G82: =E82-F82 -> #REF!

Sheet Price - Breakdown (A)
A1: PO Box 13012 Calgary RPO Beltline, AB T2R 1C6 info@luminovas.ca Phone: 587-320-0261
B2: UNITS | C2: QTY | D2: RATE | E2: TOTAL | F2: OUR COST | G2: PROFIT
A3: ABATEMENT | E3: =TEXT((SUM(E4)),"$0,000.00") -> $130,500.00 | F3: =TEXT((SUM(F4)),"$0,000.00") -> $115,250.00 | G3: =TEXT((SUM(G4)),"$0,000.00") -> $15,250.00
A4: Shower Surrounds, Damage Ceilings, and Kitchens as per scope | B4: UNITS | C4: 29 | D4: 4500 | E4: =D4*C4 -> 130500 | F4: 115250 | G4: =E4-F4 -> 15250
A5: DRYWALL | E5: =TEXT((SUM(E6:E9)),"$0,000.00") -> $204,305.50 | F5: =TEXT((SUM(F6:F9)),"$0,000.00") -> $199,240.03 | G5: =TEXT((SUM(G6:G9)),"$0,000.00") -> $5,065.47
A6: up to 2 ft | B6: LN FT | C6: 5250 | D6: 18 | E6: =D6*C6 -> 94500 | F6: 92157 | G6: =E6-F6 -> 2343
A7: Float Wall to Flat Texture | B7: SQFT | C7: 59937 | D7: 1.5 | E7: =D7*C7 -> 89905.5 | F7: 87676.41 | G7: =E7-F7 -> 2229.09
A8: Drywalled Ceiling including Insulation Texture Ceiling | B8: SQFT | C8: 900 | D8: 6 | E8: =D8*C8 -> 5400 | F8: 5266.12 | G8: =E8-F8 -> 133.88
A9: Tub Surround Boarding | B9: EACH | C9: 29 | D9: 500 | E9: =D9*C9 -> 14500 | F9: 14140.5 | G9: =E9-F9 -> 359.5
A10: FINISHING | E10: =TEXT((SUM(E11:E23)),"$0,000.00") -> $144,775.50 | F10: =TEXT((SUM(F11:F23)),"$0,000.00") -> $97,628.52 | G10: =TEXT((SUM(G11:G14)),"$0,000.00") -> $4,350.00
A11: Doors | B11: EACH | C11: 0 | D11: 310 | E11: =D11*C11 -> 0 | G11: =E11-F11 -> 0 | I11: 310
A12: New fire rated Entry Suite Door | B12: EACH | C12: 0 | D12: 1800 | E12: =D12*C12 -> 0 | G12: =E12-F12 -> 0 | I12: 1800
A13: Closet Shelves and Rod (Price per closet/storage room) | B13: EACH | C13: =84+29 -> 113 | D13: 180 | E13: =D13*C13 -> 20340 | F13: =3480+13380 -> 16860 | G13: =E13-F13 -> 3480 | I13: 180
A14: Towel bar, toilet paper holder and shower rod | B14: EACH | C14: =29 -> 29 | D14: 190 | E14: =D14*C14 -> 5510 | F14: =(85+75)*29 -> 4640 | G14: =E14-F14 -> 870 | I14: 190
A15: Closet Doors - Bypass upto 48"W and bifolds upto 36"W | B15: EACH | C15: 7 | D15: 350 | E15: =D15*C15 -> 2450 | F15: 1992.66 | G15: =E15-F15 -> 457.34 | I15: 350
A16: Closet Doors - Bypass over 48"W - upto 60"W | B16: EACH | C16: 22 | D16: 350 | E16: =D16*C16 -> 7700 | F16: 8588.75 | G16: =E16-F16 -> -888.75 | I16: 350
A17: Closet Doors - Bypass over 60"W - upto 72"W | B17: EACH | C17: 22 | D17: 350 | E17: =D17*C17 -> 7700 | F17: 8767.69 | G17: =E17-F17 -> -1067.69 | I17: 350
A18: Closet Doors - Bypass over 72"W - upto 96"W | B18: EACH | C18: 33 | D18: 350 | E18: =D18*C18 -> 11550 | F18: 14090.92 | G18: =E18-F18 -> -2540.92 | I18: 350
A19: Suite Door Closer | B19: EACH | C19: 29 | D19: 110 | E19: =D19*C19 -> 3190 | F19: =50*29 -> 1450 | G19: =E19-F19 -> 1740 | I19: 110
A20: Door Hardware (handle, hinges, and door stops) | B20: EACH | C20: =4*29 -> 116 | D20: 106 | E20: =D20*C20 -> 12296 | F20: =27*C20 -> 3132 | G20: =E20-F20 -> 9164 | I20: =65+35+6 -> 106
A21: Baseboards | B21: LN FT | C21: 7250 | D21: 4.25 | E21: =D21*C21 -> 30812.5 | F21: =1.1*C21+700*29/2 -> 18125 | G21: =E21-F21 -> 12687.5 | I21: 4.25
A22: Window and Door Casing | B22: LN FT | C22: 9284 | D22: 4.25 | E22: =D22*C22 -> 39457 | F22: =0.85*C22+700*29/2 -> 18041.4 | G22: =E22-F22 -> 21415.6 | I22: 4.25
A23: Mirror | B23: EACH | C23: 29 | D23: 130 | E23: =D23*C23 -> 3770 | F23: =66.9*C23 -> 1940.1 | G23: =E23-F23 -> 1829.9 | I23: 130
A24: FLOORING | E24: =TEXT((SUM(E25:E27)),"$0,000.00") -> $124,590.60 | F24: =TEXT((SUM(F25:F27)),"$0,000.00") -> $85,001.26 | G24: =TEXT((SUM(G25:G27)),"$0,000.00") -> $39,589.34
A25: Floor Vinyl | B25: SQFT | C25: 12516 | D25: 5.35 | E25: =D25*C25 -> 66960.6 | F25: 45043.5 | G25: =E25-F25 -> 21917.1 | I25: 5.35
A26: Removal of existing flooring and disposal | B26: SQFT | C26: 0 | D26: 0.75 | E26: =D26*C26 -> 0 | F26: =2850/2 -> 1425 | G26: =E26-F26 -> -1425 | I26: 0.75 | J26: *half of delivery fee
A27: Carpet with underlay | B27: SQFT | C27: 11526 | D27: 5 | E27: =D27*C27 -> 57630 | F27: 38532.76 | G27: =E27-F27 -> 19097.24 | I27: 5
A28: TILING | E28: =TEXT((SUM(E29:E30)),"$0,000.00") -> $23,345.00 | F28: =TEXT((SUM(F29:F30)),"$0,000.00") -> $23,200.00 | G28: =TEXT((SUM(G29:G30)),"$0,000.00") -> $0,145.00
A29: Tile Tub Surround (sq ft) | B29: SQFT | C29: =70*29 -> 2030 | D29: 11.5 | E29: =D29*C29 -> 23345 | F29: =800*29 -> 23200 | G29: =E29-F29 -> 145
A30: Back Splash (sq ft) - Kitchen and Vanity | B30: SQFT | C30: 0 | D30: 11.5 | E30: =D30*C30 -> 0 | G30: =E30-F30 -> 0
A31: CABINETS | E31: =TEXT((SUM(E32:E34)),"$0,000.00") -> $189,515.00 | F31: =TEXT((SUM(F32:F34)),"$0,000.00") -> $132,500.00 | G31: =TEXT((SUM(G32:G34)),"$0,000.00") -> $57,015.00
A32: Kitchen Cabinets (upper & lower) (linear ft) | B32: LN FT | C32: =29*16 -> 464 | D32: 295 | E32: =D32*C32 -> 136880 | F32: 132500 | G32: =E32-F32 -> 4380
A33: Kitchen Counters (linear ft) | B33: LN FT | C33: =C32 -> 464 | D33: 60 | E33: =D33*C33 -> 27840 | G33: =E33-F33 -> 27840
A34: Bathroom Vanity (3 ft) | B34: EACH | C34: 29 | D34: 855 | E34: =D34*C34 -> 24795 | G34: =E34-F34 -> 24795
A35: PLUMBING | E35: =TEXT((SUM(E36:E44)),"$0,000.00") -> $92,930.00 | F35: =TEXT((SUM(F36:F44)),"$0,000.00") -> $69,050.00 | G35: =TEXT((SUM(G36:G44)),"$0,000.00") -> $23,880.00
A36: Kitchen Sink - w/ p trap | B36: EACH | C36: 29 | D36: 590 | E36: =D36*C36 -> 17110 | F36: =29*(1100+1250) -> 68150 | G36: =E36-F36 -> -51040 | I36: 590
A37: Shut off valves | B37: EACH | C37: =29*7 -> 203 | D37: 70 | E37: =D37*C37 -> 14210 | G37: =E37-F37 -> 14210 | I37: 70
A38: Kitchen Faucet | B38: EACH | C38: 29 | D38: 300 | E38: =D38*C38 -> 8700 | G38: =E38-F38 -> 8700 | I38: 300
A39: Bathroom Sink - w/ p trap | B39: EACH | C39: 29 | D39: 325 | E39: =D39*C39 -> 9425 | G39: =E39-F39 -> 9425 | I39: 325
A40: Bathroom Faucet | B40: EACH | C40: 29 | D40: 290 | E40: =D40*C40 -> 8410 | G40: =E40-F40 -> 8410 | I40: 290
A41: New Tub | B41: EACH | C41: 0 | D41: 900 | E41: =D41*C41 -> 0 | G41: =E41-F41 -> 0 | I41: 900
A42: New Shower Valve and Trim Kit; includes Rough-in | B42: EACH | C42: 29 | D42: 585 | E42: =D42*C42 -> 16965 | G42: =E42-F42 -> 16965 | I42: 585
A43: 24" x 24" Janitor Sink | B43: EACH | C43: 1 | D43: 1000 | E43: =D43*C43 -> 1000 | F43: 900 | G43: =E43-F43 -> 100 | I43: 1000
A44: Toilet New - Standard | B44: EACH | C44: 29 | D44: 590 | E44: =D44*C44 -> 17110 | G44: =E44-F44 -> 17110 | I44: 590
A45: ELECTRICAL | E45: =TEXT((SUM(E46:E58)),"$0,000.00") -> $79,567.00 | F45: =TEXT((SUM(F46:F58)),"$0,000.00") -> $74,820.01 | G45: =TEXT((SUM(G46:G58)),"$0,000.00") -> $4,746.99
A46: 120v Receptacles | B46: EACH | C46: 408 | D46: 20 | E46: =D46*C46 -> 8160 | F46: 43065 | G46: =E46-F46 -> -34905
A47: 120v GFCI Receptacles | B47: EACH | C47: 116 | D47: 95 | E47: =D47*C47 -> 11020 | G47: =E47-F47 -> 11020
A48: Light Switches | B48: EACH | C48: 226 | D48: 20 | E48: =D48*C48 -> 4520 | G48: =E48-F48 -> 4520
A49: Cable & Phone Jack Covers | B49: EACH | C49: =29*3 -> 87 | D49: 20 | E49: =D49*C49 -> 1740 | G49: =E49-F49 -> 1740
A50: Light Fixture - Vanity Light | B50: EACH | C50: 29 | D50: 289 | E50: =D50*C50 -> 8381 | F50: 8309.04 | G50: =E50-F50 -> 71.96
A51: Replace Thermostat | B51: EACH | C51: 29 | D51: 65 | E51: =D51*C51 -> 1885 | G51: =E51-F51 -> 1885
A52: Light Fixture - Surface Mount Globe | B52: EACH | C52: 127 | D52: 75 | E52: =D52*C52 -> 9525 | F52: 9443.22 | G52: =E52-F52 -> 81.78
A53: Light Fixture - Kitchen | B53: EACH | C53: 29 | D53: 250 | E53: =D53*C53 -> 7250 | F53: 7187.75 | G53: =E53-F53 -> 62.25
A54: Replace Smoke/CO Detector | B54: EACH | C54: 29 | D54: 95 | E54: =D54*C54 -> 2755 | G54: =E54-F54 -> 2755
A55: Supply and install Bathroom Fan | B55: EACH | C55: 29 | D55: 175 | E55: =D55*C55 -> 5075 | F55: 4060 | G55: =E55-F55 -> 1015
A56: Relocate Range Outlet | B56: EACH | C56: 29 | D56: 300 | E56: =D56*C56 -> 8700 | G56: =E56-F56 -> 8700
A57: Run Power for Dishwasher | B57: EACH | C57: 29 | D57: 250 | E57: =D57*C57 -> 7250 | F57: 2755 | G57: =E57-F57 -> 4495
A58: USB Receptacle | B58: EACH | C58: =29*2 -> 58 | D58: 57 | E58: =D58*C58 -> 3306 | G58: =E58-F58 -> 3306
A59: PAINTING | E59: =TEXT((SUM(E60:E62)),"$0,000.00") -> $90,440.85 | F59: =TEXT((SUM(F60:F62)),"$0,000.00") -> $67,903.41 | G59: =TEXT((SUM(G60:G62)),"$0,000.00") -> $22,537.44
A60: Paint Walls, Doors, Trim | B60: SQFT | C60: 20791 | D60: 2.75 | E60: =D60*C60 -> 57175.25 | F60: =2.3*C60*0.92 -> 43993.756 | G60: =E60-F60 -> 13181.494 | I60: 2.75
A61: Kilz Primer | B61: SQFT | C61: 20791 | D61: 0.5 | E61: =D61*C61 -> 10395.5 | F61: =C61*0.92*0.25 -> 4781.93 | G61: =E61-F61 -> 5613.57 | I61: 0.5
A62: Paint Ceiling | B62: SQFT | C62: 20791 | D62: 1.1 | E62: =D62*C62 -> 22870.1 | F62: =1*0.92*C62 -> 19127.72 | G62: =E62-F62 -> 3742.38 | I62: 1.1
A63: BLINDS | E63: =TEXT((SUM(E64:E65)),"$0,000.00") -> $42,775.00 | F63: =TEXT((SUM(F64:F65)),"$0,000.00") -> $34,220.00 | G63: =TEXT((SUM(G64:G65)),"$0,000.00") -> $8,555.00
A64: Horizontal | B64: EACH | C64: =3*29 -> 87 | D64: 350 | E64: =D64*C64 -> 30450 | F64: =SUM(E64:E65)/1.25 -> 34220 | G64: =E64-F64 -> -3770
A65: Vertical | B65: EACH | C65: =29 -> 29 | D65: 425 | E65: =D65*C65 -> 12325 | G65: =E65-F65 -> 12325
A66: CLEANING | E66: =TEXT((SUM(E67)),"$0,000.00") -> $8,316.40 | F66: =TEXT((SUM(F67)),"$0,000.00") -> $8,316.40 | G66: =TEXT((SUM(G67)),"$0,000.00") -> $0,000.00
A67: Move-in Ready | B67: SQFT | C67: 20791 | D67: 0.4 | E67: =D67*C67 -> 8316.4 | F67: =E67 -> 8316.4 | G67: =E67-F67 -> 0
A68: APPLIANCES | E68: =TEXT((SUM(E69:E72)),"$0,000.00") -> $95,402.75 | F68: =TEXT((SUM(F69:F72)),"$0,000.00") -> $67,135.00 | G68: =TEXT((SUM(G69:G72)),"$0,000.00") -> $28,267.75
A69: Range, Fridge, and Hood fan - Stainless Steel | B69: SET | C69: 29 | D69: =1002.75+897.75+220+250-100 -> 2270.5 | E69: =D69*C69 -> 65844.5 | F69: =1780*29 -> 51620 | G69: =E69-F69 -> 14224.5
A70: Dishwasher - Supply and Install - Stainless Steel | B70: EACH | C70: 29 | D70: =719.25+100 -> 819.25 | E70: =D70*C70 -> 23758.25 | F70: =435*29 -> 12615 | G70: =E70-F70 -> 11143.25
A71: Appliance Install | B71: EACH | C71: 29 | D71: 100 | E71: =D71*C71 -> 2900 | F71: 2900 | G71: =E71-F71 -> 0
A72: Hood Fan Installation | B72: EACH | C72: 29 | D72: 100 | E72: =D72*C72 -> 2900 | G72: =E72-F72 -> 2900
A73: APPLIANCES | E73: =TEXT((SUM(E74:E76)),"$0,000.00") -> $207,350.00 | F73: =TEXT((SUM(F74:F76)),"$0,000.00") -> $32,500.00 | G73: =TEXT((SUM(G74:G76)),"$0,000.00") -> $174,850.00
A74: Contingency | B74: PER UNIT | C74: 29 | D74: 1500 | E74: =D74*C74 -> 43500 | G74: =E74-F74 -> 43500
A75: General on site labour | B75: PER UNIT | C75: 29 | D75: 2650 | E75: =D75*C75 -> 76850 | G75: =E75-F75 -> 76850
A76: Supervision | B76: PER UNIT | C76: 29 | D76: 3000 | E76: =D76*C76 -> 87000 | F76: 32500 | G76: =E76-F76 -> 54500
E77: =SUM(E4:E76) -> 1433813.6 | F77: =SUM(F4:F76) -> 1006764.6 | G77: =SUM(G4:G76) -> 427048.97
D79: price per unit without abatement | E79: =(E77-E4)/29 -> 44941.848
G82: =G77/E77 -> 0.29784135
